oauth2gh.py
picbed_oauth2_github-0.1.0.dist-info/LICENSE
picbed_oauth2_github-0.1.0.dist-info/METADATA
picbed_oauth2_github-0.1.0.dist-info/WHEEL
picbed_oauth2_github-0.1.0.dist-info/top_level.txt
picbed_oauth2_github-0.1.0.dist-info/RECORD
