Metadata-Version: 2.1
Name: picbed-oauth2-github
Version: 0.1.0
Summary: OAuth2 for GitHub
Home-page: https://github.com/staugur/picbed-oauth2-github
Author: staugur
Author-email: staugur@saintic.com
License: BSD 3-Clause
Platform: UNKNOWN
